overturemaps/__init__.py
overturemaps/cli.py
overturemaps/core.py
overturemaps/examples/geopandas_example.ipynb
overturemaps-0.17.0.dist-info/METADATA
overturemaps-0.17.0.dist-info/WHEEL
overturemaps-0.17.0.dist-info/entry_points.txt
overturemaps-0.17.0.dist-info/licenses/LICENSE
overturemaps-0.17.0.dist-info/RECORD
