Metadata-Version: 2.4
Name: overturemaps
Version: 0.17.0
Summary: Python tools for interacting with Overture Maps (overturemaps.org) data.
License: MIT
License-File: LICENSE
Author: Jacob Wasserman
Author-email: jwasserman@meta.com
Requires-Python: >=3.8,<4.0
Classifier: License :: OSI Approved :: MIT License
Classifier: Programming Language :: Python :: 3
Classifier: Programming Language :: Python :: 3.8
Classifier: Programming Language :: Python :: 3.9
Classifier: Programming Language :: Python :: 3.10
Classifier: Programming Language :: Python :: 3.11
Classifier: Programming Language :: Python :: 3.12
Classifier: Programming Language :: Python :: 3.13
Classifier: Programming Language :: Python :: 3.14
Provides-Extra: geopandas
Requires-Dist: click (>=8.1.7)
Requires-Dist: geopandas (>=1.0) ; (python_version >= "3.9") and (extra == "geopandas")
Requires-Dist: numpy (==1.24.4) ; python_version < "3.9"
Requires-Dist: numpy (>=1.26.4) ; python_version >= "3.9"
Requires-Dist: pyarrow (>=15.0.2)
Requires-Dist: shapely (>=2.0.3)
